pyannotate/__init__.py
pyannotate/cli.py
pyannotate/exac_client.py
pyannotate/vcf_annotator.py
pyvcfannotate-0.1.2.dist-info/METADATA
pyvcfannotate-0.1.2.dist-info/WHEEL
pyvcfannotate-0.1.2.dist-info/entry_points.txt
pyvcfannotate-0.1.2.dist-info/top_level.txt
pyvcfannotate-0.1.2.dist-info/RECORD
